dcclib/__init__.py
dcclib/__main__.py
dcclib/constants.py
dcclib/constructible.py
dcclib/conversion/__init__.py
dcclib/conversion/convertible.py
dcclib/conversion/json_converter.py
dcclib/extraction/__init__.py
dcclib/extraction/extractable.py
dcclib/extraction/files/__init__.py
dcclib/extraction/files/files.py
dcclib/extraction/formulae/__init__.py
dcclib/extraction/formulae/formula.py
dcclib/extraction/formulae/formula_extractor.py
dcclib/extraction/formulae/evaluator/__init__.py
dcclib/extraction/formulae/evaluator/basic_arithmetics.py
dcclib/extraction/formulae/evaluator/content_mathml_evaluator.py
dcclib/extraction/formulae/evaluator/elementary_functions.py
dcclib/extraction/formulae/evaluator/sequences_series.py
dcclib/extraction/formulae/evaluator/trigonomy.py
dcclib/signature/__init__.py
dcclib/signature/signature.py
dcclib/transformation/__init__.py
dcclib/transformation/transformable.py
dcclib/transformation/xslt.py
dcclib/validation/__init__.py
dcclib/validation/errors.py
dcclib/validation/results.py
dcclib/validation/schematron.py
dcclib/validation/validatable.py
dcclib/validation/xsd.py
dcclib/validation/schema/__init__.py
dcclib/validation/schema/dcc.sch
dcclib/validation/schema/dcc.svrl
dcclib/validation/schema/xmldsig-core-schema.xsd
dcclib/validation/schema/dcc/__init__.py
dcclib/validation/schema/dcc/v2.1.0.xsd
dcclib/validation/schema/dcc/v2.1.1.xsd
dcclib/validation/schema/dcc/v2.2.0.xsd
dcclib/validation/schema/dcc/v2.3.0.xsd
dcclib/validation/schema/dcc/v2.4.0.xsd
dcclib/validation/schema/dcc/v3.0.0.xsd
dcclib/validation/schema/dcc/v3.1.0.xsd
dcclib/validation/schema/dcc/v3.1.1.xsd
dcclib/validation/schema/dcc/v3.1.2.xsd
dcclib/validation/schema/dcc/v3.2.0.xsd
dcclib/validation/schema/dcc/v3.2.1.xsd
dcclib/validation/schema/dcc/v3.3.0.xsd
dcclib/validation/schema/dsi/__init__.py
dcclib/validation/schema/dsi/v1.0.1.xsd
dcclib/validation/schema/dsi/v1.3.0.xsd
dcclib/validation/schema/dsi/v1.3.1.xsd
dcclib/validation/schema/dsi/v2.0.0.xsd
dcclib-0.3.0.dist-info/METADATA
dcclib-0.3.0.dist-info/WHEEL
dcclib-0.3.0.dist-info/entry_points.txt
dcclib-0.3.0.dist-info/licenses/LICENSE
dcclib-0.3.0.dist-info/RECORD
