Metadata-Version: 2.4
Name: dcclib
Version: 0.3.0
Summary: A library containing modules for working with Digital Calibration Certificates (DCCs).
Author-email: Jan Loewe <jan.loewe@ptb.de>, Justin Sebastian Jagieniak <justin.jagieniak@ptb.de>
License-Expression: LGPL-3.0-or-later
License-File: LICENSE
Keywords: DCC,Digital Calibration Certificate,PTB
Requires-Python: <3.14,>=3.10
Requires-Dist: lxml>=6.0.1
Requires-Dist: mpmath>=1.3.0
Requires-Dist: prettytable>=3.16.0
Requires-Dist: saxonche>=12.9.0
Requires-Dist: signxml>=4.2.0
Requires-Dist: sympy>=1.14.0
Requires-Dist: xmlschema>=4.1.0
Provides-Extra: cli
Requires-Dist: dcclib-cli; extra == 'cli'
